setup.py
gbd_stat/Binomialdistribution.py
gbd_stat/Gaussiandistribution.py
gbd_stat/Generaldistribution.py
gbd_stat/__init__.py
gbd_stat.egg-info/PKG-INFO
gbd_stat.egg-info/SOURCES.txt
gbd_stat.egg-info/dependency_links.txt
gbd_stat.egg-info/not-zip-safe
gbd_stat.egg-info/top_level.txt