Metadata-Version: 1.0
Name: gbd-stat
Version: 0.1
Summary: Gaussian distributions
Home-page: UNKNOWN
Author: Arjun Maini
Author-email: arjunmaini007@gmail.com
License: UNKNOWN
Platform: UNKNOWN
